MANIFEST.in
README.rst
setup.cfg
setup.py
beval/__init__.py
beval/criteria.py
beval.egg-info/PKG-INFO
beval.egg-info/SOURCES.txt
beval.egg-info/dependency_links.txt
beval.egg-info/not-zip-safe
beval.egg-info/top_level.txt