Metadata-Version: 1.1
Name: beval
Version: 1.0.4
Summary: boolean expression evaluator
Home-page: https://github.com/hyw208/beval
Author: hyw208
Author-email: hyw208@gmail.com
License: Apache License, Version 2.0
Keywords: boolean expression evaluator util
Platform: UNKNOWN
Classifier: Development Status :: 5 - Production/Stable
Classifier: Intended Audience :: Developers
Classifier: Natural Language :: English
Classifier: License :: OSI Approved :: Apache Software License
Classifier: Programming Language :: Python
Classifier: Programming Language :: Python :: 2.7
